pipedream/__init__.py
pipedream/accounts/__init__.py
pipedream/accounts/client.py
pipedream/accounts/raw_client.py
pipedream/actions/__init__.py
pipedream/actions/client.py
pipedream/actions/raw_client.py
pipedream/actions/types/__init__.py
pipedream/actions/types/actions_list_request_registry.py
pipedream/app_categories/__init__.py
pipedream/app_categories/client.py
pipedream/app_categories/raw_client.py
pipedream/apps/__init__.py
pipedream/apps/client.py
pipedream/apps/raw_client.py
pipedream/apps/types/__init__.py
pipedream/apps/types/apps_list_request_sort_direction.py
pipedream/apps/types/apps_list_request_sort_key.py
pipedream/client.py
pipedream/components/__init__.py
pipedream/components/client.py
pipedream/components/raw_client.py
pipedream/components/types/__init__.py
pipedream/components/types/components_list_request_registry.py
pipedream/core/__init__.py
pipedream/core/api_error.py
pipedream/core/client_wrapper.py
pipedream/core/custom_pagination.py
pipedream/core/datetime_utils.py
pipedream/core/file.py
pipedream/core/force_multipart.py
pipedream/core/http_client.py
pipedream/core/http_response.py
pipedream/core/http_sse/__init__.py
pipedream/core/http_sse/_api.py
pipedream/core/http_sse/_decoders.py
pipedream/core/http_sse/_exceptions.py
pipedream/core/http_sse/_models.py
pipedream/core/jsonable_encoder.py
pipedream/core/oauth_token_provider.py
pipedream/core/pagination.py
pipedream/core/pydantic_utilities.py
pipedream/core/query_encoder.py
pipedream/core/remove_none_from_dict.py
pipedream/core/request_options.py
pipedream/core/serialization.py
pipedream/deployed_triggers/__init__.py
pipedream/deployed_triggers/client.py
pipedream/deployed_triggers/raw_client.py
pipedream/environment.py
pipedream/errors/__init__.py
pipedream/errors/bad_request_error.py
pipedream/errors/not_found_error.py
pipedream/errors/too_many_requests_error.py
pipedream/file_stash/__init__.py
pipedream/file_stash/client.py
pipedream/file_stash/raw_client.py
pipedream-1.1.3.dist-info/LICENSE
pipedream-1.1.3.dist-info/METADATA
pipedream-1.1.3.dist-info/WHEEL
pipedream-1.1.3.dist-info/RECORD
